{
  "name": "VS_BCI Dev",
  "image": "mcr.microsoft.com/devcontainers/python:3.11",
  "features": {
    "ghcr.io/devcontainers/features/docker-in-docker:2": {}
  },
  "customizations": {
    "vscode": {
      "extensions": [
        "ms-python.python",
        "ms-toolsai.jupyter",
        "streetsidesoftware.code-spell-checker"
      ],
      "settings": {
        "python.defaultInterpreterPath": "/usr/local/bin/python",
        "editor.formatOnSave": true
      }
    }
  },
  "postCreateCommand": "pip install -r requirements.txt",
  "forwardPorts": [8501],
  "remoteUser": "vscode",
  "runArgs": ["--init"]
}
